{
  "id": "devoir_1768716009107",
  "titre": "EVALUATION A3",
  "questions": [
    {
      "qid": "q_0",
      "label": "1",
      "competence": "C2",
      "bareme": 2,
      "reponseAttendue": "Qui ? :Les adolescents en formation professionnelle.\nQuoi ? Sédentarité élevée / Temps libre passé devant les écrans / Peu d'activité physique.\nOu ? En France / Devant les écrans / En dehors des cours.\nPourquoi ? Cela a des conséquences négatives sur leur santé physique, mentale et sociale (capital santé).\n"
    },
    {
      "qid": "q_1",
      "label": "2",
      "competence": "C3",
      "bareme": 2,
      "reponseAttendue": ""
    },
    {
      "qid": "q_2",
      "label": "3.1",
      "competence": "C2",
      "bareme": 2,
      "reponseAttendue": "Le cerveau"
    },
    {
      "qid": "q_3",
      "label": "3.2",
      "competence": "C3",
      "bareme": 2,
      "reponseAttendue": "Le message part du cerveau, descend par la moelle épinière puis emprunte le nerf moteur pour arriver jusqu'au muscle (biceps)."
    },
    {
      "qid": "q_4",
      "label": "4",
      "competence": "C2",
      "bareme": 2,
      "reponseAttendue": "Le muscle se contracte et s’épaissit lorsque les filaments d’actine et de myosine glissent les uns sur les autres à l’intérieur des myofibrilles."
    },
    {
      "qid": "q_5",
      "label": "5.1",
      "competence": "C2",
      "bareme": 1,
      "reponseAttendue": "Le glucose (90 mg).\nLe dioxygène (20 mL)"
    },
    {
      "qid": "q_6",
      "label": "5.2",
      "competence": "C2",
      "bareme": 1,
      "reponseAttendue": ""
    },
    {
      "qid": "q_7",
      "label": "5.3",
      "competence": "C2",
      "bareme": 1,
      "reponseAttendue": "Le dioxyde de carbone (CO2)"
    },
    {
      "qid": "q_8",
      "label": "6.1",
      "competence": "C2",
      "bareme": 1,
      "reponseAttendue": "Pratiquer 1h (60 minutes) d'activité physique par jour."
    },
    {
      "qid": "q_9",
      "label": "6.2",
      "competence": "C3",
      "bareme": 2,
      "reponseAttendue": "Elle permet d'éviter le surpoids et les maladies cardiovasculaires (mortalité évitable). Elle améliore le bien-être physique, mental et social."
    },
    {
      "qid": "q_10",
      "label": "7",
      "competence": "C4",
      "bareme": 2,
      "reponseAttendue": "Aller au lycée à pied ou à vélo (déplacements actifs).\nPrendre les escaliers au lieu de l'ascenseur."
    }
  ]
}